inequality_coefficients/__init__.py
inequality_coefficients/gini.py
inequality_coefficients/inequality_coefficients.py
inequality_coefficients/ratios_top.py
inequality_coefficients-1.1.0.dist-info/LICENSE
inequality_coefficients-1.1.0.dist-info/METADATA
inequality_coefficients-1.1.0.dist-info/WHEEL
inequality_coefficients-1.1.0.dist-info/top_level.txt
inequality_coefficients-1.1.0.dist-info/RECORD
