Metadata-Version: 2.1
Name: inequality-coefficients
Version: 1.1.0
Summary: Coefficients to measure inequality.
Home-page: https://github.com/Akronix/inequality_coefficients
Author: Abel 'Akronix' Serrano Juste
Author-email: akronix5@gmail.com
License: MIT
Keywords: inequality coefficient index gini ratio top
Platform: UNKNOWN
Classifier: License :: OSI Approved :: MIT License
Classifier: Programming Language :: Python :: 3
Classifier: Operating System :: OS Independent
Classifier: Topic :: Scientific/Engineering :: Mathematics
Classifier: Development Status :: 5 - Production/Stable
Classifier: Intended Audience :: Science/Research
Requires-Python: >=3
Requires-Dist: numpy
